image2gif_test/__init__.py
image2gif_test/convert.py
image2gif_test-1.0.1.dist-info/LICENSE
image2gif_test-1.0.1.dist-info/METADATA
image2gif_test-1.0.1.dist-info/WHEEL
image2gif_test-1.0.1.dist-info/top_level.txt
image2gif_test-1.0.1.dist-info/RECORD
