Metadata-Version: 2.1
Name: image2gif-test
Version: 1.0.1
Summary: Test package for distribution
Home-page: UNKNOWN
Author: ChangGeun Oh
Author-email: fiveroot4@gmail.com
License: UNKNOWN
Keywords: GIFCONVERTER,gifconverter,image2gif
Platform: UNKNOWN
Classifier: Programming Language :: Python :: 3
Classifier: License :: OSI Approved :: MIT License
Classifier: Operating System :: OS Independent
Requires-Python: >=3
License-File: LICENSE
Requires-Dist: pillow
